cow_transfer/__init__.py
cow_transfer/cow_download.py
cow_transfer/cow_upload.py
cow_transfer/main.py
cow_transfer/util.py
cow_transfer-0.0.6.dist-info/METADATA
cow_transfer-0.0.6.dist-info/WHEEL
cow_transfer-0.0.6.dist-info/entry_points.txt
cow_transfer-0.0.6.dist-info/top_level.txt
cow_transfer-0.0.6.dist-info/RECORD
