Metadata-Version: 2.1
Name: cow-transfer
Version: 0.0.6
Summary: Easily downlaod file from CowTransfer
Home-page: https://github.com/xiyoucloud/cow_transfer.git
Author: txb
Author-email: txb.sdn@gmail.com
License: MIT
Keywords: python,DownloadKit,cow_transfer
Platform: UNKNOWN
Classifier: Development Status :: 3 - Alpha
Classifier: Intended Audience :: Developers
Classifier: Programming Language :: Python :: 3
Classifier: Operating System :: Microsoft :: Windows
Requires-Dist: DownloadKit
Requires-Dist: requests
Requires-Dist: oss2
Requires-Dist: tqdm
Requires-Dist: click
